chalice_jwt/__init__.py
chalice_jwt/authenticator.py
chalice_jwt/jwt_manager.py
chalice_jwt/utils.py
chalice_jwt-1.0.1.dist-info/LICENSE
chalice_jwt-1.0.1.dist-info/METADATA
chalice_jwt-1.0.1.dist-info/WHEEL
chalice_jwt-1.0.1.dist-info/top_level.txt
chalice_jwt-1.0.1.dist-info/RECORD
